jupyter_helpers/__init__.py
jupyter_helpers/desktop_integration.py
jupyter_helpers/following_tail.py
jupyter_helpers/namespace.py
jupyter_helpers/notifications.py
jupyter_helpers/rpy2_autocompletion.py
jupyter_helpers/selective_import.py
jupyter_helpers/source.py
jupyter_helpers/table.py
jupyter_helpers/utilities.py
jupyter_helpers-0.2.3.dist-info/LICENSE
jupyter_helpers-0.2.3.dist-info/METADATA
jupyter_helpers-0.2.3.dist-info/WHEEL
jupyter_helpers-0.2.3.dist-info/top_level.txt
jupyter_helpers-0.2.3.dist-info/RECORD
