Metadata-Version: 2.1
Name: jupyter-helpers
Version: 0.2.3
Summary: A collection of helpers for using IPython in Jupyter(Lab)
Home-page: https://github.com/krassowski/jupyter-helpers
Author: Michal Krassowski
Author-email: krassowski.michal+pypi@gmail.com
License: MIT
Keywords: ipython,jupyter,jupyterlab,notebook,helpers
Platform: UNKNOWN
Classifier: Development Status :: 4 - Beta
Classifier: License :: OSI Approved :: MIT License
Classifier: Framework :: IPython
Classifier: Framework :: Jupyter
Classifier: Operating System :: Microsoft :: Windows
Classifier: Operating System :: POSIX :: Linux
Classifier: Topic :: Utilities
Classifier: Topic :: Software Development :: User Interfaces
Classifier: Topic :: Software Development :: Libraries :: Python Modules
Classifier: Intended Audience :: Developers
Classifier: Intended Audience :: Science/Research
Classifier: Programming Language :: Python :: 3.6
Classifier: Programming Language :: Python :: 3.8
Classifier: Programming Language :: Python :: 3.7
Classifier: Programming Language :: Python :: 3.9
Requires-Dist: pandas
Requires-Dist: pygments
Requires-Dist: ipywidgets
Requires-Dist: IPython
Requires-Dist: jupyterlab-widgets
